{  "data": [    {      "id": 123123,      "routeID": 4,      "gate": "s5",      "srcOffice": {        "id": 234,        "name": "СЦ Николо-Хованское",        "fullAddress": "Россия, г Москва, п Сосенское, д Николо-Хованское, ул Дельвига стр.2004",        "long": 37.4588,        "lat": 55.5979      },      "minPrice": 4500500,      "minVolume": 0,      "minBoxesCount": 23,      "dstOffices": [        {          "id": 234,          "name": "СЦ Николо-Хованское",          "fullAddress": "Россия, г Москва, п Сосенское, д Николо-Хованское, ул Дельвига стр.2004",          "long": 37.4588,          "lat": 55.5979        },        {          "id": 235,          "name": "СЦ Николо-Хованское",          "fullAddress": "Россия, г Москва, п Сосенское, д Николо-Хованское, ул Дельвига стр.2004",          "long": 37.4588,          "lat": 55.5979        },        {          "id": 236,          "name": "СЦ Николо-Хованское",          "fullAddress": "Россия, г Москва, п Сосенское, д Николо-Хованское, ул Дельвига стр.2004",          "long": 37.4588,          "lat": 55.5979        },        {          "id": 237,          "name": "СЦ Николо-Хованское",          "fullAddress": "Россия, г Москва, п Сосенское, д Николо-Хованское, ул Дельвига стр.2004",          "long": 37.4588,          "lat": 55.5979        },        {          "id": 238,          "name": "СЦ Николо-Хованское",          "fullAddress": "Россия, г Москва, п Сосенское, д Николо-Хованское, ул Дельвига стр.2004",          "long": 37.4588,          "lat": 55.5979        },        {          "id": 239,          "name": "СЦ Николо-Хованское",          "fullAddress": "Россия, г Москва, п Сосенское, д Николо-Хованское, ул Дельвига стр.2004",          "long": 37.4588,          "lat": 55.5979        },        {          "id": 240,          "name": "СЦ Николо-Хованское",          "fullAddress": "Россия, г Москва, п Сосенское, д Николо-Хованское, ул Дельвига стр.2004",          "long": 37.4588,          "lat": 55.5979        },        {          "id": 241,          "name": "СЦ Николо-Хованское",          "fullAddress": "Россия, г Москва, п Сосенское, д Николо-Хованское, ул Дельвига стр.2004",          "long": 37.4588,          "lat": 55.5979        },        {          "id": 242,          "name": "СЦ Николо-Хованское",          "fullAddress": "Россия, г Москва, п Сосенское, д Николо-Хованское, ул Дельвига стр.2004",          "long": 37.4588,          "lat": 55.5979        },        {          "id": 243,          "name": "СЦ Николо-Хованское",          "fullAddress": "Россия, г Москва, п Сосенское, д Николо-Хованское, ул Дельвига стр.2004",          "long": 37.4588,          "lat": 55.5979        }      ]    },    {      "id": 123456,      "routeID": 4,      "gate": "s5",      "srcOffice": {        "id": 234,        "name": "СЦ Николо-Хованское",        "fullAddress": "Россия, г Москва, п Сосенское, д Николо-Хованское, ул Дельвига стр.2004",        "long": 37.4588,        "lat": 55.5979      },      "minPrice": 8550,      "minVolume": 1,      "minBoxesCount": 23,      "dstOffices": []    },    {      "id": 123,      "routeID": 4,      "gate": "s5",      "srcOffice": {        "id": 234,        "name": "СЦ Николо-Хованское",        "fullAddress": "Россия, г Москва, п Сосенское, д Николо-Хованское, ул Дельвига стр.2004",        "long": 37.4588,        "lat": 55.5979      },      "minPrice": 25000,      "minVolume": 2,      "minBoxesCount": 23,      "dstOffices": [        {          "id": 234,          "name": "СЦ Николо-Хованское",          "fullAddress": "Россия, г Москва, п Сосенское, д Николо-Хованское, ул Дельвига стр.2004",          "long": 37.4588,          "lat": 55.5979        },        {          "id": 235,          "name": "СЦ Николо-Хованское",          "fullAddress": "Россия, г Москва, п Сосенское, д Николо-Хованское, ул Дельвига стр.2004",          "long": 37.4588,          "lat": 55.5979        },        {          "id": 236,          "name": "СЦ Николо-Хованское",          "fullAddress": "Россия, г Москва, п Сосенское, д Николо-Хованское, ул Дельвига стр.2004",          "long": 37.4588,          "lat": 55.5979        }      ]    },    {      "id": 123,      "routeID": 4,      "gate": "s5",      "srcOffice": {        "id": 234,        "name": "СЦ Николо-Хованское",        "fullAddress": "Россия, г Москва, п Сосенское, д Николо-Хованское, ул Дельвига стр.2004",        "long": 37.4588,        "lat": 55.5979      },      "minPrice": 70500,      "minVolume": 400,      "minBoxesCount": 23,      "dstOffices": [        {          "id": 234,          "name": "СЦ Николо-Хованское",          "fullAddress": "Россия, г Москва, п Сосенское, д Николо-Хованское, ул Дельвига стр.2004",          "long": 37.4588,          "lat": 55.5979        },        {          "id": 235,          "name": "СЦ Николо-Хованское",          "fullAddress": "Россия, г Москва, п Сосенское, д Николо-Хованское, ул Дельвига стр.2004",          "long": 37.4588,          "lat": 55.5979        },        {          "id": 236,          "name": "СЦ Николо-Хованское",          "fullAddress": "Россия, г Москва, п Сосенское, д Николо-Хованское, ул Дельвига стр.2004",          "long": 37.4588,          "lat": 55.5979        }      ]    },    {      "id": 123,      "routeID": 4,      "gate": "s5",      "srcOffice": {        "id": 234,        "name": "СЦ Николо-Хованское",        "fullAddress": "Россия, г Москва, п Сосенское, д Николо-Хованское, ул Дельвига стр.2004",        "long": 37.4588,        "lat": 55.5979      },      "minPrice": 25000,      "minVolume": 700,      "minBoxesCount": 23,      "dstOffices": [        {          "id": 234,          "name": "СЦ Николо-Хованское",          "fullAddress": "Россия, г Москва, п Сосенское, д Николо-Хованское, ул Дельвига стр.2004",          "long": 37.4588,          "lat": 55.5979        },        {          "id": 235,          "name": "СЦ Николо-Хованское",          "fullAddress": "Россия, г Москва, п Сосенское, д Николо-Хованское, ул Дельвига стр.2004",          "long": 37.4588,          "lat": 55.5979        },        {          "id": 236,          "name": "СЦ Николо-Хованское",          "fullAddress": "Россия, г Москва, п Сосенское, д Николо-Хованское, ул Дельвига стр.2004",          "long": 37.4588,          "lat": 55.5979        }      ]    },    {      "id": 123,      "routeID": 4,      "gate": "s5",      "srcOffice": {        "id": 234,        "name": "СЦ Николо-Хованское",        "fullAddress": "Россия, г Москва, п Сосенское, д Николо-Хованское, ул Дельвига стр.2004",        "long": 37.4588,        "lat": 55.5979      },      "minPrice": 3500,      "minVolume": 4,      "minBoxesCount": 23,      "dstOffices": [        {          "id": 234,          "name": "СЦ Николо-Хованское",          "fullAddress": "Россия, г Москва, п Сосенское, д Николо-Хованское, ул Дельвига стр.2004",          "long": 37.4588,          "lat": 55.5979        },        {          "id": 235,          "name": "СЦ Николо-Хованское",          "fullAddress": "Россия, г Москва, п Сосенское, д Николо-Хованское, ул Дельвига стр.2004",          "long": 37.4588,          "lat": 55.5979        },        {          "id": 236,          "name": "СЦ Николо-Хованское",          "fullAddress": "Россия, г Москва, п Сосенское, д Николо-Хованское, ул Дельвига стр.2004",          "long": 37.4588,          "lat": 55.5979        }      ]    },    {      "id": 123,      "routeID": 4,      "gate": "s5",      "srcOffice": {        "id": 234,        "name": "СЦ Николо-Хованское",        "fullAddress": "Россия, г Москва, п Сосенское, д Николо-Хованское, ул Дельвига стр.2004",        "long": 37.4588,        "lat": 55.5979      },      "minPrice": 0,      "minVolume": 4,      "minBoxesCount": 23,      "dstOffices": [        {          "id": 234,          "name": "СЦ Николо-Хованское",          "fullAddress": "Россия, г Москва, п Сосенское, д Николо-Хованское, ул Дельвига стр.2004",          "long": 37.4588,          "lat": 55.5979        },        {          "id": 235,          "name": "СЦ Николо-Хованское",          "fullAddress": "Россия, г Москва, п Сосенское, д Николо-Хованское, ул Дельвига стр.2004",          "long": 37.4588,          "lat": 55.5979        },        {          "id": 236,          "name": "СЦ Николо-Хованское",          "fullAddress": "Россия, г Москва, п Сосенское, д Николо-Хованское, ул Дельвига стр.2004",          "long": 37.4588,          "lat": 55.5979        }      ]    },    {      "id": 123,      "routeID": 4,      "gate": "s5",      "srcOffice": {        "id": 234,        "name": "СЦ Николо-Хованское",        "fullAddress": "Россия, г Москва, п Сосенское, д Николо-Хованское, ул Дельвига стр.2004",        "long": 37.4588,        "lat": 55.5979      },      "minPrice": 250000,      "minVolume": 100,      "minBoxesCount": 23,      "dstOffices": [        {          "id": 234,          "name": "СЦ Николо-Хованское",          "fullAddress": "Россия, г Москва, п Сосенское, д Николо-Хованское, ул Дельвига стр.2004",          "long": 37.4588,          "lat": 55.5979        },        {          "id": 235,          "name": "СЦ Николо-Хованское",          "fullAddress": "Россия, г Москва, п Сосенское, д Николо-Хованское, ул Дельвига стр.2004",          "long": 37.4588,          "lat": 55.5979        },        {          "id": 236,          "name": "СЦ Николо-Хованское",          "fullAddress": "Россия, г Москва, п Сосенское, д Николо-Хованское, ул Дельвига стр.2004",          "long": 37.4588,          "lat": 55.5979        }      ]    }  ]}